textset/__init__.py
textset-1.0.0.dist-info/METADATA
textset-1.0.0.dist-info/WHEEL
textset-1.0.0.dist-info/top_level.txt
textset-1.0.0.dist-info/RECORD
