Metadata-Version: 2.1
Name: textset
Version: 1.0.0
Summary: Change text setting. ex) coloring text or, underline text
Home-page: https://github.com/puter1234
Author: puter
Author-email: john.minjun.kim@gmail.com
License: MIT
Platform: UNKNOWN
Classifier: License :: OSI Approved :: MIT License
